[
  {
    "code": "600519",
    "name": "贵州茅台",
    "quote": {
      "最新价": 1270.29,
      "涨跌幅": -1.673,
      "成交额": 4199254637.0,
      "换手率": null
    },
    "tech": {
      "ok": true,
      "price": 1270.52,
      "ma5": 1274.6619999999998,
      "ma20": 1289.031,
      "ma60": 1372.799,
      "rsi14": 49.41316480630333,
      "macd": {
        "dif": -23.52826726461535,
        "dea": -26.89534450478396,
        "hist": 6.734154480337217
      },
      "boll": {
        "up": 1330.8123843716896,
        "mid": 1289.031,
        "low": 1247.2496156283103
      },
      "signals": [
        "空头排列(弱势)",
        "MACD 金叉/红柱(偏多)"
      ],
      "buy_hint": "现价已破 MA20≈1289.03;站回 MA20 上方再考虑,下方支撑看 MA60≈1372.80"
    },
    "fund_flow": {
      "日期": "2026-06-12",
      "主力净流入": 69297792.0
    },
    "valuation": {
      "PE_TTM": 19.52,
      "PB": 5.96,
      "总市值": 16149.93
    },
    "news": [
      {
        "title": "贵州茅台：余思明获聘董事会秘书",
        "time": "2026-06-12 10:27:00"
      },
      {
        "title": "贵州茅台：聘任余思明为董秘",
        "time": "2026-06-11 20:59:00"
      },
      {
        "title": "贵州茅台董事长陈华：公司目前暂无拆股计划",
        "time": "2026-06-11 16:20:00"
      }
    ]
  },
  {
    "code": "300750",
    "name": "宁德时代",
    "quote": {
      "最新价": 396.35,
      "涨跌幅": 0.38,
      "成交额": 10490244113.0,
      "换手率": null
    },
    "tech": {
      "ok": false,
      "note": "历史数据不足,跳过技术分析"
    },
    "fund_flow": {},
    "valuation": {
      "PE_TTM": 23.13,
      "PB": 5.11,
      "总市值": 18268.24
    },
    "news": [
      {
        "title": "25只个股大宗交易超5000万元",
        "time": "2026-06-15 07:59:00"
      },
      {
        "title": "宁德时代在普洱成立新公司",
        "time": "2026-06-10 13:26:00"
      },
      {
        "title": "14只个股大宗交易超5000万元",
        "time": "2026-06-11 21:34:00"
      }
    ]
  },
  {
    "code": "000858",
    "name": "五粮液",
    "quote": {
      "最新价": 79.53,
      "涨跌幅": -0.488,
      "成交额": 1489978056.0,
      "换手率": null
    },
    "tech": {
      "ok": false,
      "note": "历史数据不足,跳过技术分析"
    },
    "fund_flow": {},
    "valuation": {
      "PE_TTM": 24.62,
      "PB": 2.42,
      "总市值": 3102.18
    },
    "news": [
      {
        "title": "000858 最新公告！五粮液集团斥资不低于30亿元增持",
        "time": "2026-05-06 21:28:00"
      },
      {
        "title": "五粮液：拟免去曾从钦董事职务 其担任的董事长等职务自董事解任生效之日起自动解除",
        "time": "2026-06-08 19:13:57"
      },
      {
        "title": "五粮液：董事会同意免去曾从钦董事职务 其担任的董事长等职务自动解除",
        "time": "2026-06-08 19:24:00"
      }
    ]
  },
  {
    "code": "002594",
    "name": "比亚迪",
    "quote": {
      "最新价": 90.74,
      "涨跌幅": -0.939,
      "成交额": 2208384392.0,
      "换手率": null
    },
    "tech": {
      "ok": false,
      "note": "历史数据不足,跳过技术分析"
    },
    "fund_flow": {},
    "valuation": {
      "PE_TTM": 30.32,
      "PB": 3.6,
      "总市值": 8351.35
    },
    "news": [
      {
        "title": "比亚迪公告回应被美国国防部列入中国军工企业名单：此举无正当理由 该名单非制裁名单且不影响公司正常业务",
        "time": "2026-06-09 20:25:07"
      },
      {
        "title": "比亚迪：第二代刀片电池产能供不应求 闪充技术发布后订单爆发式增长",
        "time": "2026-06-10 17:53:25"
      },
      {
        "title": "比亚迪回应被列入美国国防部列入中国军工企业名单：此举无正当理由",
        "time": "2026-06-09 20:48:00"
      }
    ]
  },
  {
    "code": "600036",
    "name": "招商银行",
    "quote": {
      "最新价": 38.85,
      "涨跌幅": -1.246,
      "成交额": 2803107061.0,
      "换手率": null
    },
    "tech": {
      "ok": false,
      "note": "历史数据不足,跳过技术分析"
    },
    "fund_flow": {},
    "valuation": {
      "PE_TTM": 6.58,
      "PB": 0.88,
      "总市值": 9921.49
    },
    "news": [
      {
        "title": "招商银行600036.SH)：执行董事、行长王良因年龄原因辞任",
        "time": "2026-04-30 18:12:08"
      },
      {
        "title": "4.99亿元资金今日流入银行股",
        "time": "2026-06-10 21:48:00"
      },
      {
        "title": "当心账户被强平！金价年内最大回撤超28%，多家银行保证金上调至120%，个人炒金业务持续收紧",
        "time": "2026-06-12 17:29:00"
      }
    ]
  },
  {
    "code": "601318",
    "name": "中国平安",
    "quote": {
      "最新价": 53.95,
      "涨跌幅": -0.111,
      "成交额": 4487097458.0,
      "换手率": null
    },
    "tech": {
      "ok": true,
      "price": 54.02,
      "ma5": 53.214,
      "ma20": 52.265,
      "ma60": 55.09283333333333,
      "rsi14": 59.19117647058823,
      "macd": {
        "dif": -0.49692765355060686,
        "dea": -0.9179912577455452,
        "hist": 0.8421272083898768
      },
      "boll": {
        "up": 53.87667451330875,
        "mid": 52.265,
        "low": 50.65332548669125
      },
      "signals": [
        "均线纠缠(震荡)",
        "MACD 金叉/红柱(偏多)"
      ],
      "buy_hint": "回踩 MA20≈52.27 附近可关注;跌破 MA60≈55.09 减仓/止损"
    },
    "fund_flow": {
      "日期": "2026-06-12",
      "主力净流入": 244677232.0
    },
    "valuation": {
      "PE_TTM": 7.37,
      "PB": 0.96,
      "总市值": 9779.94
    },
    "news": [
      {
        "title": "中国平安601318.SH)：执行董事蔡方方辞任",
        "time": "2026-05-15 09:08:58"
      },
      {
        "title": "两融余额三连降 累计缩水137.93亿元",
        "time": "2026-06-15 09:21:00"
      },
      {
        "title": "48.05亿元资金今日流入非银金融股",
        "time": "2026-06-12 16:57:00"
      }
    ]
  }
]